synrbl/__init__.py
synrbl/__main__.py
synrbl/balancing.py
synrbl/confidence_prediction.py
synrbl/mcs_search.py
synrbl/postprocess.py
synrbl/preprocess.py
synrbl/reaction_rebalancer.py
synrbl/rsmi_utils.py
synrbl/rule_based.py
synrbl/SynAnalysis/__init__.py
synrbl/SynAnalysis/analysis_process.py
synrbl/SynAnalysis/analysis_utils.py
synrbl/SynAnalysis/eda_analysis.py
synrbl/SynAnalysis/feature_analysis.py
synrbl/SynAnalysis/scoring_function.dump
synrbl/SynAnalysis/visualizer.py
synrbl/SynChemImputer/__init__.py
synrbl/SynChemImputer/appel_reaction.py
synrbl/SynChemImputer/compounds_template.json
synrbl/SynChemImputer/curate_oxidation.py
synrbl/SynChemImputer/curate_reduction.py
synrbl/SynChemImputer/molecule_standardizer.py
synrbl/SynChemImputer/peroxide_imputer.py
synrbl/SynChemImputer/post_process.py
synrbl/SynChemImputer/reaction_template.json
synrbl/SynCmd/__init__.py
synrbl/SynCmd/cmd_benchmark.py
synrbl/SynCmd/cmd_run.py
synrbl/SynCmd/logging.py
synrbl/SynMCSImputer/__init__.py
synrbl/SynMCSImputer/compound_rules.json
synrbl/SynMCSImputer/expand_rules.json
synrbl/SynMCSImputer/mcs_based_method.py
synrbl/SynMCSImputer/merge.py
synrbl/SynMCSImputer/merge_rules.json
synrbl/SynMCSImputer/merge_rules_example.json
synrbl/SynMCSImputer/rules.py
synrbl/SynMCSImputer/structure.py
synrbl/SynMCSImputer/utils.py
synrbl/SynMCSImputer/MissingGraph/__init__.py
synrbl/SynMCSImputer/MissingGraph/find_graph_dict.py
synrbl/SynMCSImputer/MissingGraph/find_missing_graphs.py
synrbl/SynMCSImputer/MissingGraph/molcurator.py
synrbl/SynMCSImputer/MissingGraph/refinement_uncertainty.py
synrbl/SynMCSImputer/MissingGraph/uncertainty_graph.py
synrbl/SynMCSImputer/SubStructure/__init__.py
synrbl/SynMCSImputer/SubStructure/extract_common_mcs.py
synrbl/SynMCSImputer/SubStructure/mcs_graph_detector.py
synrbl/SynMCSImputer/SubStructure/mcs_process.py
synrbl/SynMCSImputer/SubStructure/substructure_analyzer.py
synrbl/SynProcessor/__init__.py
synrbl/SynProcessor/check_carbon_balance.py
synrbl-1.0.5.dist-info/METADATA
synrbl-1.0.5.dist-info/WHEEL
synrbl-1.0.5.dist-info/licenses/LICENSE
synrbl-1.0.5.dist-info/RECORD
