Metadata-Version: 2.4
Name: synrbl
Version: 1.0.5
Summary: Synthesis Rebalancing Framework for Computational Chemistry
Project-URL: homepage, https://github.com/TieuLongPhan/SynRBL
Project-URL: source, https://github.com/TieuLongPhan/SynRBL
Project-URL: issues, https://github.com/TieuLongPhan/SynRBL/issues
Author-email: Tieu Long Phan <long.tieu_phan@uni-leipzig.de>, Klaus Weinbauer <klaus@bioinf.uni-leipzig.de>
License-File: LICENSE
Classifier: License :: OSI Approved :: MIT License
Classifier: Operating System :: OS Independent
Classifier: Programming Language :: Python :: 3
Requires-Python: >=3.11
Requires-Dist: fgutils<=0.2.3,>=0.1.3
Requires-Dist: imbalanced-learn>=0.14.0
Requires-Dist: reportlab>=4.1.0
Requires-Dist: scikit-learn==1.7.2
Requires-Dist: synkit>=1.0.1
Requires-Dist: xgboost<=3.0.0,>=2.0.3
